abbu/__init__.py
abbu/consts.py
abbu/generator.py
abbu/spec.py
abbu-0.1.0.dist-info/LICENSE
abbu-0.1.0.dist-info/METADATA
abbu-0.1.0.dist-info/WHEEL
abbu-0.1.0.dist-info/top_level.txt
abbu-0.1.0.dist-info/RECORD
