Metadata-Version: 2.1
Name: abbu
Version: 0.1.0
Summary: AI Code Generation
Author-email: Jawad Ahmad <jahmad3393@gmail.com>
Classifier: Programming Language :: Python :: 3
Classifier: License :: OSI Approved :: MIT License
Classifier: Operating System :: OS Independent
Requires-Python: >=3.11
License-File: LICENSE
Requires-Dist: openai >=1.35.6
